mcp_server_nacos/__init__.py
mcp_server_nacos/__main__.py
mcp_server_nacos/nacos_tools.py
mcp_server_nacos/server.py
nacos_mcp_server-0.1.2.dist-info/METADATA
nacos_mcp_server-0.1.2.dist-info/WHEEL
nacos_mcp_server-0.1.2.dist-info/entry_points.txt
nacos_mcp_server-0.1.2.dist-info/licenses/LICENSE
nacos_mcp_server-0.1.2.dist-info/RECORD
