Metadata-Version: 2.4
Name: nacos-mcp-server
Version: 0.1.2
Summary: A simple Nacos MCP Server
License-File: LICENSE
Requires-Python: >=3.13
Requires-Dist: httpx>=0.28.1
Requires-Dist: mcp[cli]>=1.6.0
